yaqd_newport/VERSION
yaqd_newport/__init__.py
yaqd_newport/__version__.py
yaqd_newport/_newport_conex_agp.py
yaqd_newport/_newport_motor.py
yaqd_newport/_newport_smc100.py
yaqd_newport/_serial.py
yaqd_newport/newport-conex-agp.avpr
yaqd_newport/newport-conex-agp.toml
yaqd_newport/newport-smc100.avpr
yaqd_newport/newport-smc100.toml
yaqd_newport-2025.4.0.dist-info/entry_points.txt
yaqd_newport-2025.4.0.dist-info/licenses/LICENSE
yaqd_newport-2025.4.0.dist-info/WHEEL
yaqd_newport-2025.4.0.dist-info/METADATA
yaqd_newport-2025.4.0.dist-info/RECORD
