Metadata-Version: 2.4
Name: yaqd-newport
Version: 2025.4.0
Summary: yaq daemons for Newport hardware
Maintainer: yaq developers
Requires-Python: >=3.7
Classifier: Development Status :: 4 - Beta
Classifier: Intended Audience :: Science/Research
Classifier: License :: OSI Approved :: GNU Lesser General Public License v3 (LGPLv3)
Classifier: Natural Language :: English
Classifier: Programming Language :: Python :: 3
Classifier: Programming Language :: Python :: 3.7
Classifier: Programming Language :: Python :: 3.8
Classifier: Programming Language :: Python :: 3.9
Classifier: Programming Language :: Python :: 3.10
Classifier: Topic :: Scientific/Engineering
License-File: LICENSE
Requires-Dist: yaqd-core>=2023.6.0
Requires-Dist: pyserial
Project-URL: Homepage, https://yaq.fyi
Project-URL: Issues, https://github.com/yaq-project/yaqd-newport/issues
Project-URL: Source, https://github.com/yaq-project/yaqd-newport
